Metadata-Version: 1.0
Name: satori-imager
Version: 0.1.1
Summary: The System Imager of the Satori-Suite
Home-page: https://github.com/satori-ng/
Author: Satori-NG org
Author-email: satori_ng@email.com
License: UNKNOWN
Platform: UNKNOWN
